gattctl.py
setup.py
gatt/__init__.py
gatt/errors.py
gatt/gatt.py
gatt/gatt_linux.py
gatt/gatt_stubs.py
gatt.egg-info/PKG-INFO
gatt.egg-info/SOURCES.txt
gatt.egg-info/dependency_links.txt
gatt.egg-info/entry_points.txt
gatt.egg-info/top_level.txt