Metadata-Version: 1.1
Name: gatt
Version: 0.2.3
Summary: Bluetooth GATT SDK for Python
Home-page: https://github.com/getsenic/gatt-python
Author: Senic GmbH
Author-email: developers@senic.com
License: MIT
Download-URL: https://github.com/getsenic/gatt-python/archive/0.1.0.tar.gz
Keywords: gatt
Platform: UNKNOWN
